{
	"Language": "Français",
	"Payoff": "Simplement un wiki à base de fichiers à plats markdown sans base de données...",
	"Subtitle": "Wiki basé sur des fichiers plats de markdown",
	"TooltipSidebar": "Menu latéral",
	"TooltipPrint": "Imprimer",
	"TooltipSignIn": "Se connecter pour modifier ou<br>ajouter de nouveaux documents",
	"TooltipSettings": "Paramètres",
	"TooltipNewDocument": "Ajouter un nouveau document",
	"TooltipEditDocument": "Éditer",
	"TooltipRestoreVersion": "Restaurer cette version",
	"TooltipRestoreVersionConfirm": "Voulez-vous vraiment restaurer cette version du document ?",
	"TooltipCancelEditing": "Annuler l'édition",
	"TooltipImages": "Images",
	"TooltipDeleteDocument": "Supprimer ce contenu",
	"TooltipDeleteDocumentConfirm": "Voulez-vous vraiment supprimer ce contenu ?",
	"TooltipVersions": "Afficher les versions",
	"TooltipVersioning": "Sauvegarder la version actuelle",
	"TooltipSave": "Enregistrer",
	"Search": "Rechercher dans le wiki...",
	"SearchResults": "Résultats de la recherche",
	"SearchNoResults": "Aucun résultat trouvé pour",
	"Logout": "Se déconnecter",
	"LastUpdate": "Cette page a été éditée pour la dernière fois le",
	"PoweredBy": "Propulsé par",
	"CookieAgreement": "Accord relatif aux cookies",
	"CookieButtonDisagree": "REJETER",
	"CookieButtonAgree": "ACCEPTER",
	"Images": "Images",
	"ImagesBrowse": "Parcourir",
	"ImagesSelect": "Sélectionner une image à envoyer",
	"ImagesSubmit": "Envoyer",
	"Attachments": "Pièces jointes",
	"AttachmentsBrowse": "Parcourir",
	"AttachmentsSelect": "Sélectionner un fichier à envoyer",
	"AttachmentsSubmit": "Envoyer",
	"Versions": "Versions",
	"AuthPassword": "Insérer le code d'authentification...",
	"AuthSubmit": "ENVOYER",
	"ConfirmLoadDraft": "Un brouillon a été trouvé, voulez-vous le charger ?",
	"PromptNewDocument": "Saisir le nouveau chemin d'accès au document (comme section/sous-section/titre)",
	"Settings": "Paramètres",
	"SettingsStored": "Paramètres mémorisés !",
	"SettingsConfigure": "Paramétrer le wiki",
	"SettingsTitle": "Nom",
	"SettingsSubtitle": "Épigraphe (sous-titre)",
	"SettingsOwner": "Propriétaire",
	"SettingsOwnerPlaceholder": "Propriétaire du contenu",
	"SettingsNotice": "Avis de droit d'auteur",
	"SettingsNoticePlaceholder": "Contenu de l'avis de droit d'auteur",
	"SettingsPrivacy": "Bannière de confidentialité",
	"SettingsPrivacyPlaceholder": "Bannière de confidentialité pour la conformité RGPD",
	"SettingsEditCode": "Modifier le code d'authentification",
	"SettingsEditCodePlaceholder": "Choisir un mot de passe fort pour l'édition",
	"SettingsViewCode": "Afficher le code d'authentification",
	"SettingsViewCodePlaceholder": "Laisser ce champ vide pour rendre ce wiki public.",
	"SettingsColor": "Couleur",
	"SettingsColorPlaceholder": "Choix de la couleur principale",
	"SettingsDark": "Mode Sombre",
	"SettingsGtag": "Tag Google Analytics",
	"SettingsGtagPlaceholder": "Insérer G-TAG",
	"SettingsLanguage": "Langue",
	"SettingsCancel": "Annuler",
	"SettingsSubmit": "Sauvegarder",
	"SubmitAuthSuccess": "Authentification acceptée !",
	"SubmitAuthInvalid": "Code d'authentification incorrect !",
	"SubmitNotAuthenticated": "Vous n'êtes pas authentifié(e) !",
	"SubmitDocumentVersionNotFound": "La version du document n'a pas été trouvée !",
	"SubmitDocumentPathCannotBeEmpty": "Le chemin d'accès au document ne peut pas être vide !",
	"SubmitDocumentContentCannotBeEmpty": "Le contenu du document ne peut pas être vide !",
	"SubmitDocumentError": "Une erreur s'est produite lors de l'enregistrement du document !",
	"SubmitDocumentSaved": "Document enregistré avec succès !",
	"SubmitDocumentRestored": "Document restauré avec succès !",
	"SubmitDocumentDeleted": "Document supprimé !"
}